Metadata-Version: 2.1
Name: djangoplicity-icalendar
Version: 2.1
Summary: iCalendar parser/generator
Home-page: https://github.com/djangoplicity/djangoplicity-icalendar
Author: MaxM
Author-email: maxm@mxm.dk
License: GPL2.1
Download-URL: https://github.com/djangoplicity/djangoplicity-icalendar/archive/refs/tags/2.1.tar.gz
Keywords: calendar icalendar
Platform: All
Classifier: Development Status :: 5 - Production/Stable
Classifier: Intended Audience :: Developers
Classifier: License :: OSI Approved :: GNU General Public License (GPL)
Classifier: Operating System :: OS Independent
License-File: LICENSE.txt
